{"data":[{"names":[{"name":"User","count":1},{"name":"IUser","count":1},{"name":"anonymous","count":1}],"files":[{"name":"User","type":"literal","src":"// ...\nexport type User = {\n  displayName: string;\n  email: string;\n  password: string;\n};\n// ...","pos":[54,117],"offset":26,"lines":[6,10],"properties":[{"name":"displayName","type":"string"},{"name":"email","type":"string"},{"name":"password","type":"string"}],"file":"src/model.ts","srcHgl":{"type":"root","children":[{"type":"element","tagName":"span","properties":{"className":["token","comment"]},"children":[{"type":"text","value":"// ..."}]},{"type":"text","value":"\n"},{"type":"element","tagName":"span","properties":{"className":["token","keyword"]},"children":[{"type":"text","value":"export"}]},{"type":"text","value":" "},{"type":"element","tagName":"span","properties":{"className":["token","keyword"]},"children":[{"type":"text","value":"type"}]},{"type":"text","value":" "},{"type":"element","tagName":"span","properties":{"className":["token","class-name"]},"children":[{"type":"text","value":"User"}]},{"type":"text","value":" "},{"type":"element","tagName":"span","properties":{"className":["token","operator"]},"children":[{"type":"text","value":"="}]},{"type":"text","value":" "},{"type":"element","tagName":"span","properties":{"className":["token","punctuation"]},"children":[{"type":"text","value":"{"}]},{"type":"text","value":"\n  displayName"},{"type":"element","tagName":"span","properties":{"className":["token","operator"]},"children":[{"type":"text","value":":"}]},{"type":"text","value":" "},{"type":"element","tagName":"span","properties":{"className":["token","builtin"]},"children":[{"type":"text","value":"string"}]},{"type":"element","tagName":"span","properties":{"className":["token","punctuation"]},"children":[{"type":"text","value":";"}]},{"type":"text","value":"\n  email"},{"type":"element","tagName":"span","properties":{"className":["token","operator"]},"children":[{"type":"text","value":":"}]},{"type":"text","value":" "},{"type":"element","tagName":"span","properties":{"className":["token","builtin"]},"children":[{"type":"text","value":"string"}]},{"type":"element","tagName":"span","properties":{"className":["token","punctuation"]},"children":[{"type":"text","value":";"}]},{"type":"text","value":"\n  password"},{"type":"element","tagName":"span","properties":{"className":["token","operator"]},"children":[{"type":"text","value":":"}]},{"type":"text","value":" "},{"type":"element","tagName":"span","properties":{"className":["token","builtin"]},"children":[{"type":"text","value":"string"}]},{"type":"element","tagName":"span","properties":{"className":["token","punctuation"]},"children":[{"type":"text","value":";"}]},{"type":"text","value":"\n"},{"type":"element","tagName":"span","properties":{"className":["token","punctuation"]},"children":[{"type":"text","value":"}"}]},{"type":"element","tagName":"span","properties":{"className":["token","punctuation"]},"children":[{"type":"text","value":";"}]},{"type":"text","value":"\n"},{"type":"element","tagName":"span","properties":{"className":["token","comment"]},"children":[{"type":"text","value":"// ..."}]}]}},{"name":"IUser","type":"interface","src":"// ...\ninterface IUser {\n  displayName: string;\n  email: string;\n  password: string;\n}\n// ...\n// ...","pos":[14,93],"offset":7,"lines":[3,7],"properties":[{"name":"displayName","type":"string"},{"name":"email","type":"string"},{"name":"password","type":"string"}],"file":"src/auth.ts","srcHgl":{"type":"root","children":[{"type":"element","tagName":"span","properties":{"className":["token","comment"]},"children":[{"type":"text","value":"// ..."}]},{"type":"text","value":"\n"},{"type":"element","tagName":"span","properties":{"className":["token","keyword"]},"children":[{"type":"text","value":"interface"}]},{"type":"text","value":" "},{"type":"element","tagName":"span","properties":{"className":["token","class-name"]},"children":[{"type":"text","value":"IUser"}]},{"type":"text","value":" "},{"type":"element","tagName":"span","properties":{"className":["token","punctuation"]},"children":[{"type":"text","value":"{"}]},{"type":"text","value":"\n  displayName"},{"type":"element","tagName":"span","properties":{"className":["token","operator"]},"children":[{"type":"text","value":":"}]},{"type":"text","value":" "},{"type":"element","tagName":"span","properties":{"className":["token","builtin"]},"children":[{"type":"text","value":"string"}]},{"type":"element","tagName":"span","properties":{"className":["token","punctuation"]},"children":[{"type":"text","value":";"}]},{"type":"text","value":"\n  email"},{"type":"element","tagName":"span","properties":{"className":["token","operator"]},"children":[{"type":"text","value":":"}]},{"type":"text","value":" "},{"type":"element","tagName":"span","properties":{"className":["token","builtin"]},"children":[{"type":"text","value":"string"}]},{"type":"element","tagName":"span","properties":{"className":["token","punctuation"]},"children":[{"type":"text","value":";"}]},{"type":"text","value":"\n  password"},{"type":"element","tagName":"span","properties":{"className":["token","operator"]},"children":[{"type":"text","value":":"}]},{"type":"text","value":" "},{"type":"element","tagName":"span","properties":{"className":["token","builtin"]},"children":[{"type":"text","value":"string"}]},{"type":"element","tagName":"span","properties":{"className":["token","punctuation"]},"children":[{"type":"text","value":";"}]},{"type":"text","value":"\n"},{"type":"element","tagName":"span","properties":{"className":["token","punctuation"]},"children":[{"type":"text","value":"}"}]},{"type":"text","value":"\n"},{"type":"element","tagName":"span","properties":{"className":["token","comment"]},"children":[{"type":"text","value":"// ..."}]},{"type":"text","value":"\n"},{"type":"element","tagName":"span","properties":{"className":["token","comment"]},"children":[{"type":"text","value":"// ..."}]}]}},{"name":"anonymous","type":"literal","src":"async function saveUser(\n  user: {\n    displayName: string;\n    email: string;\n    password: string;\n  }) {\n  await db.createUser(user);","pos":[195,266],"offset":33,"lines":[18,22],"properties":[{"name":"displayName","type":"string"},{"name":"email","type":"string"},{"name":"password","type":"string"}],"file":"src/api.ts","srcHgl":{"type":"root","children":[{"type":"element","tagName":"span","properties":{"className":["token","keyword"]},"children":[{"type":"text","value":"async"}]},{"type":"text","value":" "},{"type":"element","tagName":"span","properties":{"className":["token","keyword"]},"children":[{"type":"text","value":"function"}]},{"type":"text","value":" "},{"type":"element","tagName":"span","properties":{"className":["token","function"]},"children":[{"type":"text","value":"saveUser"}]},{"type":"element","tagName":"span","properties":{"className":["token","punctuation"]},"children":[{"type":"text","value":"("}]},{"type":"text","value":"\n  user"},{"type":"element","tagName":"span","properties":{"className":["token","operator"]},"children":[{"type":"text","value":":"}]},{"type":"text","value":" "},{"type":"element","tagName":"span","properties":{"className":["token","punctuation"]},"children":[{"type":"text","value":"{"}]},{"type":"text","value":"\n    displayName"},{"type":"element","tagName":"span","properties":{"className":["token","operator"]},"children":[{"type":"text","value":":"}]},{"type":"text","value":" "},{"type":"element","tagName":"span","properties":{"className":["token","builtin"]},"children":[{"type":"text","value":"string"}]},{"type":"element","tagName":"span","properties":{"className":["token","punctuation"]},"children":[{"type":"text","value":";"}]},{"type":"text","value":"\n    email"},{"type":"element","tagName":"span","properties":{"className":["token","operator"]},"children":[{"type":"text","value":":"}]},{"type":"text","value":" "},{"type":"element","tagName":"span","properties":{"className":["token","builtin"]},"children":[{"type":"text","value":"string"}]},{"type":"element","tagName":"span","properties":{"className":["token","punctuation"]},"children":[{"type":"text","value":";"}]},{"type":"text","value":"\n    password"},{"type":"element","tagName":"span","properties":{"className":["token","operator"]},"children":[{"type":"text","value":":"}]},{"type":"text","value":" "},{"type":"element","tagName":"span","properties":{"className":["token","builtin"]},"children":[{"type":"text","value":"string"}]},{"type":"element","tagName":"span","properties":{"className":["token","punctuation"]},"children":[{"type":"text","value":";"}]},{"type":"text","value":"\n  "},{"type":"element","tagName":"span","properties":{"className":["token","punctuation"]},"children":[{"type":"text","value":"}"}]},{"type":"element","tagName":"span","properties":{"className":["token","punctuation"]},"children":[{"type":"text","value":")"}]},{"type":"text","value":" "},{"type":"element","tagName":"span","properties":{"className":["token","punctuation"]},"children":[{"type":"text","value":"{"}]},{"type":"text","value":"\n  "},{"type":"element","tagName":"span","properties":{"className":["token","keyword"]},"children":[{"type":"text","value":"await"}]},{"type":"text","value":" db"},{"type":"element","tagName":"span","properties":{"className":["token","punctuation"]},"children":[{"type":"text","value":"."}]},{"type":"element","tagName":"span","properties":{"className":["token","function"]},"children":[{"type":"text","value":"createUser"}]},{"type":"element","tagName":"span","properties":{"className":["token","punctuation"]},"children":[{"type":"text","value":"("}]},{"type":"text","value":"user"},{"type":"element","tagName":"span","properties":{"className":["token","punctuation"]},"children":[{"type":"text","value":")"}]},{"type":"element","tagName":"span","properties":{"className":["token","punctuation"]},"children":[{"type":"text","value":";"}]}]}}],"group":"renamed","properties":[{"name":"displayName","type":"string"},{"name":"email","type":"string"},{"name":"password","type":"string"}]}],"meta":{"projectName":"example","projectFilesScanned":6,"projectLocScanned":167,"projectTypesScanned":4,"projectFilesWithTypesDeclarations":3,"scannedAt":"2023-04-29T16:58:52+03:00","scanDuration":0,"reportSize":687289}}